{
  "part 1": {
    "1": {
      "app_num_tx": 0,
      "app_num_endpoint_rx": 0,
      "app_num_lost": 0,
      "app_reliability": 100,
      "app_num_queue_drops": 0,
      "app_num_tx_limit_drops": 0,
      "app_num_routing_drops": 0,
      "app_num_scheduling_drops": 0,
      "app_num_other_drops": 0,
      "tsch_eb_tx": 21,
      "tsch_eb_rx": 0,
      "tsch_keepalive_tx": 0,
      "tsch_keepalive_rx": 0,
      "mac_tx": 93,
      "mac_tx_unicast": 6,
      "mac_acked": 5,
      "mac_rx": 420,
      "mac_rx_error": 0,
      "mac_rx_collision": 373,
      "mac_ack_error": 0,
      "mac_parent_tx_unicast": 0,
      "mac_parent_acked": 0,
      "mac_parent_rx": 0,
      "slots_rx_idle": 193,
      "slots_rx_scanning": 0,
      "slots_rx_packet": 69,
      "slots_rx_packet_tx_ack": 351,
      "slots_tx_packet": 87,
      "slots_tx_packet_rx_ack": 6,
      "tsch_join_time_sec": 0,
      "tsch_num_parent_changes": 0,
      "app_latency_min_s": null,
      "app_latency_avg_s": 0,
      "app_latency_max_s": null,
      "app_latencies": [],
      "radio_duty_cycle": 0.035,
      "radio_duty_cycle_joined": 0.035,
      "charge_uc": 4210.637,
      "charge_joined_uc": 4210.637,
      "avg_current_uA": 3.509,
      "avg_current_joined_uA": 3.509,
      "routing_tx": 73,
      "routing_rx": 61,
      "routing_join_time_sec": 0,
      "routing_num_parent_changes": 0
    },
    "2": {
      "app_num_tx": 6,
      "app_num_endpoint_rx": 0,
      "app_num_lost": 0,
      "app_reliability": 100,
      "app_num_queue_drops": 0,
      "app_num_tx_limit_drops": 0,
      "app_num_routing_drops": 0,
      "app_num_scheduling_drops": 0,
      "app_num_other_drops": 0,
      "tsch_eb_tx": 1,
      "tsch_eb_rx": 5,
      "tsch_keepalive_tx": 0,
      "tsch_keepalive_rx": 0,
      "mac_tx": 88,
      "mac_tx_unicast": 36,
      "mac_acked": 4,
      "mac_rx": 38,
      "mac_rx_error": 0,
      "mac_rx_collision": 354,
      "mac_ack_error": 0,
      "mac_parent_tx_unicast": 11,
      "mac_parent_acked": 0,
      "mac_parent_rx": 3,
      "slots_rx_idle": 532,
      "slots_rx_scanning": 398,
      "slots_rx_packet": 27,
      "slots_rx_packet_tx_ack": 1,
      "slots_tx_packet": 52,
      "slots_tx_packet_rx_ack": 36,
      "tsch_join_time_sec": 62.446,
      "tsch_num_parent_changes": 3,
      "app_latency_min_s": null,
      "app_latency_avg_s": 0,
      "app_latency_max_s": null,
      "app_latencies": [],
      "radio_duty_cycle": 0.429,
      "radio_duty_cycle_joined": 0.098,
      "charge_uc": 39466.524,
      "charge_joined_uc": 11606.524,
      "avg_current_uA": 32.89,
      "avg_current_joined_uA": 9.672,
      "routing_tx": 73,
      "routing_rx": 21,
      "routing_join_time_sec": 214.012,
      "routing_num_parent_changes": 2
    },
    "3": {
      "app_num_tx": 323,
      "app_num_endpoint_rx": 322,
      "app_num_lost": 0,
      "app_reliability": 100,
      "app_num_queue_drops": 0,
      "app_num_tx_limit_drops": 0,
      "app_num_routing_drops": 0,
      "app_num_scheduling_drops": 0,
      "app_num_other_drops": 0,
      "tsch_eb_tx": 18,
      "tsch_eb_rx": 17,
      "tsch_keepalive_tx": 0,
      "tsch_keepalive_rx": 0,
      "mac_tx": 436,
      "mac_tx_unicast": 358,
      "mac_acked": 329,
      "mac_rx": 90,
      "mac_rx_error": 2,
      "mac_rx_collision": 244,
      "mac_ack_error": 0,
      "mac_parent_tx_unicast": 358,
      "mac_parent_acked": 323,
      "mac_parent_rx": 41,
      "slots_rx_idle": 464,
      "slots_rx_scanning": 801,
      "slots_rx_packet": 59,
      "slots_rx_packet_tx_ack": 1,
      "slots_tx_packet": 78,
      "slots_tx_packet_rx_ack": 358,
      "tsch_join_time_sec": 125.677,
      "tsch_num_parent_changes": 2,
      "app_latency_min_s": 0,
      "app_latency_avg_s": 2.377860248447202,
      "app_latency_max_s": 10.512,
      "app_latencies": [
        1.255,
        1.569,
        3.295,
        2.354,
        8.002,
        5.805,
        5.648,
        4.55,
        3.295,
        4.236,
        4.55,
        3.138,
        3.452,
        3.452,
        2.04,
        2.04,
        2.51,
        2.197,
        2.981,
        1.569,
        0.785,
        1.098,
        0,
        0,
        0.941,
        2.981,
        0.785,
        2.51,
        2.354,
        1.412,
        1.569,
        0.471,
        1.726,
        0.785,
        0.471,
        1.098,
        3.138,
        0.471,
        2.04,
        1.726,
        3.609,
        1.412,
        5.648,
        6.904,
        5.178,
        3.923,
        5.492,
        3.452,
        2.981,
        4.393,
        2.197,
        2.04,
        0.628,
        0.157,
        2.51,
        2.04,
        3.295,
        1.098,
        2.824,
        2.51,
        0.785,
        2.51,
        1.883,
        1.098,
        1.569,
        2.197,
        2.667,
        3.766,
        1.883,
        1.569,
        2.51,
        2.981,
        3.295,
        2.197,
        1.883,
        1.098,
        0.941,
        2.51,
        2.667,
        1.569,
        2.824,
        2.197,
        2.04,
        1.255,
        1.412,
        1.412,
        1.412,
        0,
        1.726,
        2.354,
        3.452,
        1.098,
        1.726,
        0.471,
        0.941,
        1.569,
        2.824,
        1.098,
        1.412,
        0.157,
        0.941,
        1.255,
        1.726,
        2.51,
        1.412,
        0.941,
        1.098,
        0.941,
        2.04,
        0.628,
        2.197,
        3.295,
        2.667,
        2.197,
        1.569,
        1.726,
        2.197,
        1.255,
        0.628,
        2.04,
        0.784,
        0.628,
        0.471,
        0.157,
        1.098,
        0.157,
        1.883,
        0.471,
        0.628,
        0.314,
        2.04,
        1.569,
        1.726,
        2.667,
        0.628,
        2.353,
        1.726,
        1.883,
        2.51,
        3.138,
        0.941,
        1.412,
        1.726,
        2.197,
        2.04,
        3.138,
        1.726,
        0.784,
        1.883,
        4.079,
        1.569,
        1.412,
        1.412,
        1.569,
        1.726,
        3.766,
        1.726,
        0.157,
        2.353,
        1.412,
        0.784,
        2.197,
        0.941,
        2.04,
        3.138,
        1.569,
        1.412,
        0.784,
        2.353,
        2.04,
        2.981,
        2.824,
        2.04,
        2.353,
        4.079,
        4.236,
        1.883,
        0.784,
        0.628,
        1.883,
        0.157,
        1.412,
        0.628,
        1.883,
        0.471,
        1.255,
        1.569,
        1.569,
        1.255,
        1.255,
        2.353,
        2.353,
        3.766,
        3.138,
        2.667,
        0.941,
        0.314,
        1.255,
        2.04,
        7.06,
        8.316,
        7.845,
        6.904,
        6.904,
        3.922,
        3.295,
        5.491,
        4.55,
        2.04,
        1.412,
        2.667,
        0.628,
        0.314,
        0.941,
        1.569,
        1.412,
        1.255,
        1.883,
        0.941,
        2.197,
        0.628,
        2.04,
        1.883,
        2.667,
        0.628,
        1.726,
        1.569,
        1.098,
        0.941,
        2.353,
        1.726,
        0.471,
        2.353,
        3.452,
        1.098,
        2.197,
        2.51,
        0.784,
        2.197,
        2.197,
        2.197,
        1.569,
        1.412,
        1.569,
        1.726,
        1.883,
        1.098,
        2.824,
        0,
        0.314,
        0.784,
        1.569,
        1.883,
        1.726,
        2.51,
        2.981,
        2.353,
        2.353,
        3.922,
        1.883,
        1.098,
        2.51,
        0.314,
        1.098,
        0.941,
        0.628,
        2.197,
        1.412,
        2.04,
        2.04,
        2.04,
        0.941,
        2.197,
        1.569,
        3.609,
        2.981,
        2.353,
        0,
        10.512,
        9.885,
        9.571,
        8.943,
        8.943,
        8.473,
        7.531,
        7.531,
        5.962,
        5.648,
        6.747,
        4.079,
        3.609,
        3.922,
        4.236,
        2.04,
        2.197,
        1.255,
        2.824,
        2.353,
        0.314,
        0.314,
        7.845,
        7.531,
        6.904,
        6.59,
        7.06,
        5.805,
        4.393,
        4.393,
        4.864,
        4.707,
        2.197,
        4.079,
        2.04,
        0.471,
        1.883,
        0.628,
        0.157,
        1.098,
        2.197,
        1.412,
        0.628,
        1.412
      ],
      "radio_duty_cycle": 0.753,
      "radio_duty_cycle_joined": 0.085,
      "charge_uc": 66192.983,
      "charge_joined_uc": 10122.983,
      "avg_current_uA": 55.162,
      "avg_current_joined_uA": 8.436,
      "routing_tx": 73,
      "routing_rx": 51,
      "routing_join_time_sec": 165.373,
      "routing_num_parent_changes": 1
    },
    "4": {
      "app_num_tx": 145,
      "app_num_endpoint_rx": 1,
      "app_num_lost": 109,
      "app_reliability": 0.9090909090909038,
      "app_num_queue_drops": 16,
      "app_num_tx_limit_drops": 0,
      "app_num_routing_drops": 93,
      "app_num_scheduling_drops": 0,
      "app_num_other_drops": 0,
      "tsch_eb_tx": 13,
      "tsch_eb_rx": 5,
      "tsch_keepalive_tx": 0,
      "tsch_keepalive_rx": 0,
      "mac_tx": 320,
      "mac_tx_unicast": 259,
      "mac_acked": 204,
      "mac_rx": 337,
      "mac_rx_error": 1,
      "mac_rx_collision": 274,
      "mac_ack_error": 0,
      "mac_parent_tx_unicast": 156,
      "mac_parent_acked": 129,
      "mac_parent_rx": 72,
      "slots_rx_idle": 221,
      "slots_rx_scanning": 404,
      "slots_rx_packet": 39,
      "slots_rx_packet_tx_ack": 289,
      "slots_tx_packet": 61,
      "slots_tx_packet_rx_ack": 259,
      "tsch_join_time_sec": 63.388,
      "tsch_num_parent_changes": 62,
      "app_latency_min_s": 8.943,
      "app_latency_avg_s": 8.943,
      "app_latency_max_s": 8.943,
      "app_latencies": [
        8.943
      ],
      "radio_duty_cycle": 0.377,
      "radio_duty_cycle_joined": 0.041,
      "charge_uc": 33101.507,
      "charge_joined_uc": 4821.507,
      "avg_current_uA": 27.585,
      "avg_current_joined_uA": 4.018,
      "routing_tx": 169,
      "routing_rx": 105,
      "routing_join_time_sec": 81.117,
      "routing_num_parent_changes": 62
    },
    "5": {
      "app_num_tx": 47,
      "app_num_endpoint_rx": 15,
      "app_num_lost": 7,
      "app_reliability": 68.18181818181819,
      "app_num_queue_drops": 7,
      "app_num_tx_limit_drops": 0,
      "app_num_routing_drops": 0,
      "app_num_scheduling_drops": 0,
      "app_num_other_drops": 0,
      "tsch_eb_tx": 6,
      "tsch_eb_rx": 4,
      "tsch_keepalive_tx": 0,
      "tsch_keepalive_rx": 0,
      "mac_tx": 122,
      "mac_tx_unicast": 67,
      "mac_acked": 21,
      "mac_rx": 47,
      "mac_rx_error": 0,
      "mac_rx_collision": 329,
      "mac_ack_error": 0,
      "mac_parent_tx_unicast": 35,
      "mac_parent_acked": 19,
      "mac_parent_rx": 7,
      "slots_rx_idle": 552,
      "slots_rx_scanning": 1,
      "slots_rx_packet": 36,
      "slots_rx_packet_tx_ack": 7,
      "slots_tx_packet": 55,
      "slots_tx_packet_rx_ack": 67,
      "tsch_join_time_sec": 0.157,
      "tsch_num_parent_changes": 9,
      "app_latency_min_s": 9.728,
      "app_latency_avg_s": 17.290466666666664,
      "app_latency_max_s": 22.907,
      "app_latencies": [
        10.042,
        9.728,
        15.533,
        14.435,
        14.749,
        14.905,
        11.454,
        22.437,
        22.907,
        21.338,
        20.554,
        20.554,
        20.868,
        19.456,
        20.397
      ],
      "radio_duty_cycle": 0.102,
      "radio_duty_cycle_joined": 0.101,
      "charge_uc": 12112.86,
      "charge_joined_uc": 12042.86,
      "avg_current_uA": 10.094,
      "avg_current_joined_uA": 10.036,
      "routing_tx": 73,
      "routing_rx": 35,
      "routing_join_time_sec": 29.497,
      "routing_num_parent_changes": 9
    },
    "6": {
      "app_num_tx": 9,
      "app_num_endpoint_rx": 0,
      "app_num_lost": 0,
      "app_reliability": 100,
      "app_num_queue_drops": 0,
      "app_num_tx_limit_drops": 0,
      "app_num_routing_drops": 0,
      "app_num_scheduling_drops": 0,
      "app_num_other_drops": 0,
      "tsch_eb_tx": 1,
      "tsch_eb_rx": 8,
      "tsch_keepalive_tx": 0,
      "tsch_keepalive_rx": 0,
      "mac_tx": 84,
      "mac_tx_unicast": 36,
      "mac_acked": 1,
      "mac_rx": 54,
      "mac_rx_error": 1,
      "mac_rx_collision": 326,
      "mac_ack_error": 0,
      "mac_parent_tx_unicast": 11,
      "mac_parent_acked": 0,
      "mac_parent_rx": 6,
      "slots_rx_idle": 495,
      "slots_rx_scanning": 801,
      "slots_rx_packet": 37,
      "slots_rx_packet_tx_ack": 0,
      "slots_tx_packet": 48,
      "slots_tx_packet_rx_ack": 36,
      "tsch_join_time_sec": 125.677,
      "tsch_num_parent_changes": 5,
      "app_latency_min_s": null,
      "app_latency_avg_s": 0,
      "app_latency_max_s": null,
      "app_latencies": [],
      "radio_duty_cycle": 0.758,
      "radio_duty_cycle_joined": 0.091,
      "charge_uc": 66869.303,
      "charge_joined_uc": 10799.303,
      "avg_current_uA": 55.726,
      "avg_current_joined_uA": 9,
      "routing_tx": 70,
      "routing_rx": 26,
      "routing_join_time_sec": 389.112,
      "routing_num_parent_changes": 4
    },
    "7": {
      "app_num_tx": 217,
      "app_num_endpoint_rx": 0,
      "app_num_lost": 189,
      "app_reliability": 0,
      "app_num_queue_drops": 19,
      "app_num_tx_limit_drops": 0,
      "app_num_routing_drops": 170,
      "app_num_scheduling_drops": 0,
      "app_num_other_drops": 0,
      "tsch_eb_tx": 16,
      "tsch_eb_rx": 8,
      "tsch_keepalive_tx": 0,
      "tsch_keepalive_rx": 0,
      "mac_tx": 430,
      "mac_tx_unicast": 355,
      "mac_acked": 292,
      "mac_rx": 265,
      "mac_rx_error": 0,
      "mac_rx_collision": 255,
      "mac_ack_error": 0,
      "mac_parent_tx_unicast": 250,
      "mac_parent_acked": 206,
      "mac_parent_rx": 73,
      "slots_rx_idle": 317,
      "slots_rx_scanning": 1,
      "slots_rx_packet": 48,
      "slots_rx_packet_tx_ack": 209,
      "slots_tx_packet": 75,
      "slots_tx_packet_rx_ack": 355,
      "tsch_join_time_sec": 0.157,
      "tsch_num_parent_changes": 39,
      "app_latency_min_s": null,
      "app_latency_avg_s": 0,
      "app_latency_max_s": null,
      "app_latencies": [],
      "radio_duty_cycle": 0.059,
      "radio_duty_cycle_joined": 0.058,
      "charge_uc": 6985.918,
      "charge_joined_uc": 6915.918,
      "avg_current_uA": 5.822,
      "avg_current_joined_uA": 5.763,
      "routing_tx": 161,
      "routing_rx": 108,
      "routing_join_time_sec": 37.499,
      "routing_num_parent_changes": 39
    },
    "8": {
      "app_num_tx": 5,
      "app_num_endpoint_rx": 0,
      "app_num_lost": 0,
      "app_reliability": 100,
      "app_num_queue_drops": 0,
      "app_num_tx_limit_drops": 0,
      "app_num_routing_drops": 0,
      "app_num_scheduling_drops": 0,
      "app_num_other_drops": 0,
      "tsch_eb_tx": 1,
      "tsch_eb_rx": 5,
      "tsch_keepalive_tx": 0,
      "tsch_keepalive_rx": 0,
      "mac_tx": 84,
      "mac_tx_unicast": 30,
      "mac_acked": 2,
      "mac_rx": 67,
      "mac_rx_error": 0,
      "mac_rx_collision": 336,
      "mac_ack_error": 0,
      "mac_parent_tx_unicast": 8,
      "mac_parent_acked": 0,
      "mac_parent_rx": 6,
      "slots_rx_idle": 539,
      "slots_rx_scanning": 1,
      "slots_rx_packet": 62,
      "slots_rx_packet_tx_ack": 0,
      "slots_tx_packet": 54,
      "slots_tx_packet_rx_ack": 30,
      "tsch_join_time_sec": 0.157,
      "tsch_num_parent_changes": 3,
      "app_latency_min_s": null,
      "app_latency_avg_s": 0,
      "app_latency_max_s": null,
      "app_latencies": [],
      "radio_duty_cycle": 0.1,
      "radio_duty_cycle_joined": 0.099,
      "charge_uc": 11829.241,
      "charge_joined_uc": 11759.241,
      "avg_current_uA": 9.858,
      "avg_current_joined_uA": 9.8,
      "routing_tx": 75,
      "routing_rx": 41,
      "routing_join_time_sec": 252.923,
      "routing_num_parent_changes": 2
    },
    "global-stats for this duration": {
      "app-packets-sent": [
        {
          "total": 752,
          "name": "Number of application packets sent"
        }
      ],
      "app-packets-received": [
        {
          "total": 338,
          "name": "Number of application packets received"
        }
      ],
      "app-packets-lost": [
        {
          "total": 305,
          "name": "Number of application packets lost"
        }
      ],
      "current-consumed": [
        {
          "name": "Current consumed",
          "unit": "mA",
          "mean": 0.201
        }
      ],
      "current-consumed-when-joined": [
        {
          "name": "Current consumed",
          "unit": "mA",
          "mean": 0.06
        }
      ],
      "e2e-delivery": [
        {
          "value": 52.56609642301711,
          "name": "E2E delivery ratio",
          "unit": "%"
        },
        {
          "value": 47.43390357698289,
          "name": "E2E loss ratio",
          "unit": "%"
        }
      ],
      "e2e-latency": [
        {
          "name": "E2E latency",
          "min": 0,
          "max": 22.907,
          "unit": "s",
          "mean": 3.0590857988165645
        }
      ]
    }
  }
}