{
  "1": {
    "app_num_tx": 0,
    "app_num_endpoint_rx": 0,
    "app_num_lost": 0,
    "app_reliability": 100,
    "app_num_queue_drops": 0,
    "app_num_tx_limit_drops": 0,
    "app_num_routing_drops": 0,
    "app_num_scheduling_drops": 0,
    "app_num_other_drops": 0,
    "tsch_eb_tx": 117,
    "tsch_eb_rx": 0,
    "tsch_keepalive_tx": 0,
    "tsch_keepalive_rx": 0,
    "mac_tx": 671,
    "mac_tx_unicast": 219,
    "mac_acked": 140,
    "mac_rx": 1921,
    "mac_rx_error": 427,
    "mac_rx_collision": 1167,
    "mac_ack_error": 1,
    "mac_parent_tx_unicast": 0,
    "mac_parent_acked": 0,
    "mac_parent_rx": 0,
    "slots_rx_idle": 1717,
    "slots_rx_scanning": 0,
    "slots_rx_packet": 414,
    "slots_rx_packet_tx_ack": 1507,
    "slots_tx_packet": 452,
    "slots_tx_packet_rx_ack": 219,
    "tsch_join_time_sec": 0,
    "tsch_num_parent_changes": 0,
    "app_latency_min_s": null,
    "app_latency_avg_s": 0,
    "app_latency_max_s": null,
    "app_latencies": [],
    "radio_duty_cycle": 0.172,
    "radio_duty_cycle_joined": 0.172,
    "charge_uc": 37459.402,
    "charge_joined_uc": 37459.402,
    "avg_current_uA": 5.203,
    "avg_current_joined_uA": 5.203,
    "routing_tx": 490,
    "routing_rx": 468,
    "routing_join_time_sec": 0,
    "routing_num_parent_changes": 0
  },
  "2": {
    "app_num_tx": 206,
    "app_num_endpoint_rx": 147,
    "app_num_lost": 43,
    "app_reliability": 77.36842105263158,
    "app_num_queue_drops": 6,
    "app_num_tx_limit_drops": 3,
    "app_num_routing_drops": 34,
    "app_num_scheduling_drops": 0,
    "app_num_other_drops": 0,
    "tsch_eb_tx": 68,
    "tsch_eb_rx": 73,
    "tsch_keepalive_tx": 0,
    "tsch_keepalive_rx": 0,
    "mac_tx": 1466,
    "mac_tx_unicast": 1105,
    "mac_acked": 744,
    "mac_rx": 1050,
    "mac_rx_error": 209,
    "mac_rx_collision": 1671,
    "mac_ack_error": 86,
    "mac_parent_tx_unicast": 923,
    "mac_parent_acked": 546,
    "mac_parent_rx": 173,
    "slots_rx_idle": 2792,
    "slots_rx_scanning": 0,
    "slots_rx_packet": 369,
    "slots_rx_packet_tx_ack": 608,
    "slots_tx_packet": 361,
    "slots_tx_packet_rx_ack": 1105,
    "tsch_join_time_sec": 0,
    "tsch_num_parent_changes": 92,
    "app_latency_min_s": 4.393,
    "app_latency_avg_s": 102.3435918367347,
    "app_latency_max_s": 2020.401,
    "app_latencies": [
      725.035,
      784.029,
      11.767,
      37.97,
      78.45,
      76.096,
      2020.401,
      1100.183,
      1100.183,
      1916.69,
      1826.944,
      110.928,
      166.471,
      170.08,
      173.374,
      77.038,
      58.681,
      34.675,
      27.614,
      45.03,
      47.227,
      44.246,
      36.871,
      40.951,
      37.97,
      41.422,
      34.989,
      45.658,
      47.384,
      49.894,
      36.558,
      51.463,
      34.832,
      39.853,
      42.52,
      15.062,
      14.278,
      4.707,
      4.55,
      7.217,
      5.178,
      6.59,
      11.611,
      7.06,
      5.491,
      11.14,
      989.098,
      7.688,
      4.707,
      10.669,
      10.512,
      20.397,
      13.023,
      8.473,
      8.473,
      10.826,
      16.161,
      21.966,
      11.767,
      7.06,
      4.393,
      17.102,
      26.045,
      23.221,
      11.14,
      37.656,
      33.263,
      32.478,
      25.261,
      28.556,
      36.401,
      33.42,
      26.673,
      13.807,
      17.102,
      22.123,
      19.612,
      18.043,
      13.964,
      9.1,
      6.119,
      4.707,
      11.924,
      16.318,
      13.65,
      18.514,
      29.654,
      37.342,
      38.911,
      38.754,
      40.166,
      43.618,
      59.465,
      55.072,
      55.229,
      46.129,
      37.656,
      35.773,
      29.968,
      33.42,
      19.456,
      13.964,
      23.378,
      16.004,
      4.707,
      12.709,
      10.042,
      12.238,
      16.788,
      18.828,
      18.671,
      29.654,
      22.594,
      20.083,
      17.102,
      29.026,
      42.049,
      48.639,
      45.344,
      40.951,
      46.756,
      44.873,
      51.463,
      57.112,
      57.739,
      56.641,
      50.522,
      33.42,
      23.535,
      23.378,
      17.73,
      21.181,
      20.868,
      53.974,
      49.737,
      43.618,
      43.618,
      38.911,
      36.558,
      44.56,
      42.363,
      40.009,
      32.478,
      35.302,
      37.028,
      33.733,
      36.244
    ],
    "radio_duty_cycle": 0.279,
    "radio_duty_cycle_joined": 0.279,
    "charge_uc": 60912.435,
    "charge_joined_uc": 60912.435,
    "avg_current_uA": 8.46,
    "avg_current_joined_uA": 8.46,
    "routing_tx": 739,
    "routing_rx": 554,
    "routing_join_time_sec": 262.651,
    "routing_num_parent_changes": 92
  },
  "3": {
    "app_num_tx": 447,
    "app_num_endpoint_rx": 447,
    "app_num_lost": 0,
    "app_reliability": 100,
    "app_num_queue_drops": 0,
    "app_num_tx_limit_drops": 0,
    "app_num_routing_drops": 0,
    "app_num_scheduling_drops": 0,
    "app_num_other_drops": 0,
    "tsch_eb_tx": 116,
    "tsch_eb_rx": 105,
    "tsch_keepalive_tx": 0,
    "tsch_keepalive_rx": 0,
    "mac_tx": 2224,
    "mac_tx_unicast": 1751,
    "mac_acked": 1474,
    "mac_rx": 1538,
    "mac_rx_error": 400,
    "mac_rx_collision": 909,
    "mac_ack_error": 13,
    "mac_parent_tx_unicast": 1747,
    "mac_parent_acked": 1354,
    "mac_parent_rx": 291,
    "slots_rx_idle": 2182,
    "slots_rx_scanning": 0,
    "slots_rx_packet": 421,
    "slots_rx_packet_tx_ack": 1012,
    "slots_tx_packet": 473,
    "slots_tx_packet_rx_ack": 1751,
    "tsch_join_time_sec": 0,
    "tsch_num_parent_changes": 1,
    "app_latency_min_s": 0,
    "app_latency_avg_s": 3.705519015659958,
    "app_latency_max_s": 43.932,
    "app_latencies": [
      0.784,
      43.932,
      29.497,
      11.924,
      0.785,
      1.412,
      1.883,
      10.512,
      1.412,
      2.667,
      7.531,
      0.314,
      4.393,
      0.941,
      0.785,
      0,
      8.473,
      0.471,
      0.628,
      2.354,
      0.628,
      2.824,
      1.726,
      2.04,
      3.138,
      1.098,
      2.354,
      1.255,
      3.609,
      2.981,
      1.883,
      2.667,
      1.569,
      2.197,
      3.766,
      8.316,
      8.629,
      2.824,
      0.314,
      0.941,
      4.864,
      10.355,
      18.043,
      4.236,
      1.569,
      2.353,
      2.353,
      20.711,
      13.023,
      0.628,
      5.805,
      0.314,
      4.079,
      4.079,
      1.255,
      0.314,
      3.922,
      2.197,
      0,
      9.885,
      0,
      29.497,
      26.359,
      15.69,
      4.079,
      4.393,
      1.883,
      11.924,
      6.59,
      2.353,
      0.157,
      15.219,
      10.512,
      4.079,
      0.628,
      7.374,
      0.941,
      5.178,
      6.119,
      10.198,
      3.138,
      2.353,
      2.197,
      4.864,
      0.628,
      1.883,
      2.51,
      2.04,
      1.883,
      24.633,
      21.966,
      23.378,
      15.376,
      7.845,
      5.491,
      4.707,
      5.491,
      3.138,
      1.883,
      0.157,
      0.471,
      1.255,
      0.314,
      0.784,
      2.04,
      1.412,
      2.353,
      4.393,
      3.295,
      0.628,
      2.824,
      1.883,
      1.726,
      1.883,
      2.04,
      2.197,
      2.353,
      0.941,
      2.04,
      2.51,
      1.098,
      1.883,
      2.353,
      0,
      0.784,
      0.471,
      1.098,
      1.726,
      2.51,
      0.314,
      1.569,
      1.098,
      0,
      2.353,
      0.784,
      0.941,
      1.098,
      0.314,
      0.471,
      2.353,
      2.04,
      1.883,
      1.726,
      1.098,
      0.628,
      2.353,
      2.04,
      1.726,
      0.784,
      2.197,
      2.353,
      0.471,
      1.569,
      1.883,
      4.079,
      0.157,
      1.098,
      1.098,
      2.667,
      2.04,
      2.981,
      0.628,
      3.609,
      0.941,
      1.726,
      1.255,
      1.255,
      1.726,
      5.805,
      2.824,
      4.393,
      7.374,
      2.197,
      1.098,
      1.883,
      3.138,
      1.255,
      4.864,
      2.353,
      0,
      2.51,
      2.667,
      3.138,
      1.569,
      2.197,
      4.393,
      5.491,
      0.784,
      2.353,
      4.236,
      2.04,
      4.393,
      0.157,
      2.51,
      2.04,
      4.707,
      0.784,
      0.471,
      8.629,
      1.883,
      3.922,
      3.295,
      2.51,
      3.138,
      2.197,
      2.51,
      1.098,
      4.55,
      1.412,
      3.138,
      4.393,
      0.314,
      0.941,
      3.138,
      0,
      4.707,
      5.178,
      2.51,
      1.255,
      1.569,
      0,
      3.609,
      4.079,
      3.138,
      4.236,
      5.805,
      3.609,
      2.51,
      4.079,
      9.1,
      1.883,
      0,
      0.157,
      3.922,
      7.374,
      5.178,
      0.628,
      2.353,
      5.805,
      1.726,
      4.079,
      1.726,
      1.412,
      3.766,
      6.747,
      8.316,
      1.255,
      3.452,
      3.138,
      5.805,
      7.845,
      4.236,
      6.904,
      9.1,
      10.826,
      0.784,
      0,
      4.393,
      4.393,
      5.021,
      2.667,
      2.667,
      0.784,
      0.157,
      0.157,
      0,
      0,
      2.04,
      0.471,
      1.255,
      0.941,
      0,
      2.353,
      1.569,
      1.098,
      0.784,
      1.255,
      2.04,
      1.726,
      0.628,
      2.353,
      2.353,
      2.51,
      1.726,
      2.197,
      0.471,
      1.569,
      0.784,
      1.569,
      1.255,
      2.04,
      2.197,
      4.079,
      0.628,
      2.353,
      0.941,
      0.628,
      7.374,
      2.667,
      4.864,
      2.981,
      2.353,
      4.707,
      1.098,
      2.04,
      2.353,
      0.314,
      1.255,
      2.981,
      1.255,
      0.628,
      0.784,
      3.922,
      2.981,
      0.628,
      2.981,
      1.726,
      4.079,
      2.981,
      4.55,
      3.766,
      0.471,
      6.276,
      4.55,
      2.51,
      3.452,
      7.217,
      0.941,
      2.51,
      4.864,
      6.119,
      2.353,
      3.922,
      2.04,
      4.55,
      3.138,
      4.864,
      4.55,
      1.883,
      3.138,
      5.178,
      2.824,
      2.197,
      4.707,
      0.314,
      1.412,
      4.079,
      5.648,
      4.707,
      6.59,
      8.943,
      3.295,
      2.51,
      3.138,
      4.864,
      3.609,
      2.353,
      4.55,
      5.021,
      3.609,
      3.922,
      2.51,
      9.885,
      5.805,
      3.138,
      7.531,
      0.471,
      2.197,
      3.766,
      2.353,
      0.314,
      1.412,
      2.824,
      7.06,
      9.414,
      9.257,
      7.374,
      5.805,
      9.571,
      7.531,
      1.569,
      3.766,
      3.138,
      2.04,
      7.217,
      9.1,
      3.295,
      5.178,
      2.51,
      6.276,
      9.257,
      0.784,
      3.766,
      0.314,
      4.55,
      10.355,
      8.316,
      5.335,
      9.257,
      1.883,
      4.707,
      2.981,
      3.452,
      6.433,
      6.276,
      4.55,
      5.805,
      6.119,
      3.609,
      6.904,
      2.824,
      1.726,
      4.55,
      2.51,
      4.393,
      1.412,
      2.51,
      9.728,
      8.786,
      11.297,
      12.238,
      11.611,
      4.55,
      5.648,
      2.51,
      3.766,
      1.883,
      2.04,
      2.353,
      1.098,
      1.412,
      2.197,
      2.04,
      1.255,
      2.197,
      0.314,
      2.981,
      2.51,
      1.412,
      0.314,
      2.667,
      1.255,
      2.197,
      2.51,
      2.04,
      1.883,
      1.412
    ],
    "radio_duty_cycle": 0.218,
    "radio_duty_cycle_joined": 0.218,
    "charge_uc": 47604.202,
    "charge_joined_uc": 47604.202,
    "avg_current_uA": 6.612,
    "avg_current_joined_uA": 6.612,
    "routing_tx": 608,
    "routing_rx": 537,
    "routing_join_time_sec": 38.911,
    "routing_num_parent_changes": 1
  },
  "4": {
    "app_num_tx": 58,
    "app_num_endpoint_rx": 0,
    "app_num_lost": 37,
    "app_reliability": 0,
    "app_num_queue_drops": 7,
    "app_num_tx_limit_drops": 5,
    "app_num_routing_drops": 25,
    "app_num_scheduling_drops": 0,
    "app_num_other_drops": 0,
    "tsch_eb_tx": 31,
    "tsch_eb_rx": 15,
    "tsch_keepalive_tx": 0,
    "tsch_keepalive_rx": 0,
    "mac_tx": 631,
    "mac_tx_unicast": 313,
    "mac_acked": 196,
    "mac_rx": 548,
    "mac_rx_error": 667,
    "mac_rx_collision": 774,
    "mac_ack_error": 3,
    "mac_parent_tx_unicast": 204,
    "mac_parent_acked": 115,
    "mac_parent_rx": 123,
    "slots_rx_idle": 3218,
    "slots_rx_scanning": 0,
    "slots_rx_packet": 358,
    "slots_rx_packet_tx_ack": 175,
    "slots_tx_packet": 318,
    "slots_tx_packet_rx_ack": 313,
    "tsch_join_time_sec": 0,
    "tsch_num_parent_changes": 76,
    "app_latency_min_s": null,
    "app_latency_avg_s": 0,
    "app_latency_max_s": null,
    "app_latencies": [],
    "radio_duty_cycle": 0.322,
    "radio_duty_cycle_joined": 0.322,
    "charge_uc": 70206.381,
    "charge_joined_uc": 70206.381,
    "avg_current_uA": 9.751,
    "avg_current_joined_uA": 9.751,
    "routing_tx": 603,
    "routing_rx": 419,
    "routing_join_time_sec": 150.781,
    "routing_num_parent_changes": 76
  },
  "5": {
    "app_num_tx": 294,
    "app_num_endpoint_rx": 247,
    "app_num_lost": 39,
    "app_reliability": 86.36363636363636,
    "app_num_queue_drops": 11,
    "app_num_tx_limit_drops": 4,
    "app_num_routing_drops": 24,
    "app_num_scheduling_drops": 0,
    "app_num_other_drops": 0,
    "tsch_eb_tx": 84,
    "tsch_eb_rx": 65,
    "tsch_keepalive_tx": 0,
    "tsch_keepalive_rx": 0,
    "mac_tx": 1444,
    "mac_tx_unicast": 1074,
    "mac_acked": 729,
    "mac_rx": 1141,
    "mac_rx_error": 402,
    "mac_rx_collision": 1238,
    "mac_ack_error": 69,
    "mac_parent_tx_unicast": 866,
    "mac_parent_acked": 513,
    "mac_parent_rx": 207,
    "slots_rx_idle": 2705,
    "slots_rx_scanning": 0,
    "slots_rx_packet": 489,
    "slots_rx_packet_tx_ack": 587,
    "slots_tx_packet": 370,
    "slots_tx_packet_rx_ack": 1074,
    "tsch_join_time_sec": 0,
    "tsch_num_parent_changes": 70,
    "app_latency_min_s": 2.353,
    "app_latency_avg_s": 28.68661133603239,
    "app_latency_max_s": 978.585,
    "app_latencies": [
      2.981,
      3.609,
      6.276,
      3.138,
      2.354,
      3.452,
      4.079,
      8.002,
      3.295,
      3.295,
      2.824,
      14.906,
      5.962,
      3.766,
      9.257,
      4.707,
      4.707,
      6.904,
      4.079,
      3.922,
      6.276,
      4.236,
      4.079,
      3.138,
      3.295,
      4.079,
      8.473,
      17.73,
      6.904,
      4.864,
      4.393,
      2.824,
      23.378,
      17.259,
      8.786,
      2.353,
      8.002,
      4.079,
      8.159,
      17.102,
      2.51,
      4.864,
      3.609,
      2.51,
      2.981,
      2.667,
      8.629,
      2.667,
      2.667,
      2.667,
      10.983,
      3.922,
      29.654,
      18.985,
      13.023,
      4.236,
      2.824,
      15.062,
      12.709,
      3.295,
      3.295,
      3.922,
      2.51,
      2.353,
      6.747,
      9.571,
      4.55,
      4.393,
      6.59,
      7.531,
      11.297,
      3.922,
      2.667,
      4.236,
      10.355,
      4.864,
      2.51,
      4.864,
      7.217,
      2.353,
      29.811,
      29.968,
      5.021,
      12.866,
      4.55,
      8.473,
      14.278,
      5.178,
      11.297,
      5.805,
      6.59,
      4.864,
      5.335,
      8.159,
      9.257,
      6.119,
      5.962,
      5.805,
      5.962,
      25.261,
      7.688,
      10.042,
      8.943,
      4.236,
      4.707,
      5.021,
      7.688,
      4.393,
      19.142,
      11.611,
      11.14,
      13.493,
      11.767,
      18.671,
      164.274,
      160.666,
      87.707,
      81.588,
      81.588,
      67.467,
      63.858,
      47.541,
      175.1,
      45.187,
      177.925,
      65.584,
      121.754,
      21.966,
      17.416,
      8.316,
      18.671,
      53.032,
      32.792,
      27.301,
      25.418,
      38.597,
      42.991,
      40.323,
      43.775,
      35.773,
      36.244,
      29.811,
      35.93,
      47.227,
      45.658,
      34.361,
      42.049,
      35.773,
      34.047,
      46.442,
      978.585,
      14.592,
      14.592,
      23.849,
      28.399,
      27.301,
      5.491,
      17.73,
      16.318,
      17.259,
      19.926,
      13.65,
      15.062,
      17.416,
      10.983,
      32.321,
      23.692,
      20.868,
      42.991,
      52.718,
      40.323,
      50.679,
      52.248,
      36.244,
      42.991,
      30.595,
      26.359,
      18.514,
      19.769,
      22.28,
      25.732,
      19.456,
      17.259,
      5.962,
      15.062,
      24.633,
      20.868,
      22.594,
      47.698,
      39.696,
      47.698,
      38.597,
      33.106,
      40.637,
      44.716,
      43.147,
      62.132,
      60.25,
      58.994,
      42.52,
      27.928,
      24.163,
      12.238,
      15.847,
      14.905,
      17.259,
      10.983,
      15.062,
      9.257,
      15.062,
      27.301,
      24.006,
      27.928,
      26.83,
      21.338,
      16.318,
      49.423,
      51.149,
      42.363,
      50.365,
      38.754,
      45.815,
      42.52,
      50.208,
      67.781,
      59.308,
      55.856,
      34.675,
      30.282,
      31.223,
      17.259,
      36.087,
      29.968,
      25.418,
      58.053,
      55.229,
      47.384,
      40.637,
      39.068,
      44.716,
      45.03,
      47.698,
      42.049,
      42.52,
      29.811,
      38.597,
      45.03
    ],
    "radio_duty_cycle": 0.271,
    "radio_duty_cycle_joined": 0.271,
    "charge_uc": 59014.375,
    "charge_joined_uc": 59014.375,
    "avg_current_uA": 8.196,
    "avg_current_joined_uA": 8.196,
    "routing_tx": 704,
    "routing_rx": 630,
    "routing_join_time_sec": 155.645,
    "routing_num_parent_changes": 70
  },
  "6": {
    "app_num_tx": 179,
    "app_num_endpoint_rx": 117,
    "app_num_lost": 40,
    "app_reliability": 74.52229299363057,
    "app_num_queue_drops": 9,
    "app_num_tx_limit_drops": 11,
    "app_num_routing_drops": 20,
    "app_num_scheduling_drops": 0,
    "app_num_other_drops": 0,
    "tsch_eb_tx": 61,
    "tsch_eb_rx": 53,
    "tsch_keepalive_tx": 0,
    "tsch_keepalive_rx": 0,
    "mac_tx": 934,
    "mac_tx_unicast": 592,
    "mac_acked": 287,
    "mac_rx": 625,
    "mac_rx_error": 775,
    "mac_rx_collision": 797,
    "mac_ack_error": 56,
    "mac_parent_tx_unicast": 380,
    "mac_parent_acked": 168,
    "mac_parent_rx": 122,
    "slots_rx_idle": 3166,
    "slots_rx_scanning": 0,
    "slots_rx_packet": 354,
    "slots_rx_packet_tx_ack": 218,
    "slots_tx_packet": 342,
    "slots_tx_packet_rx_ack": 592,
    "tsch_join_time_sec": 0,
    "tsch_num_parent_changes": 77,
    "app_latency_min_s": 17.573,
    "app_latency_avg_s": 90.37840170940171,
    "app_latency_max_s": 1921.084,
    "app_latencies": [
      219.503,
      120.342,
      77.979,
      591.356,
      1921.084,
      17.573,
      90.061,
      78.921,
      112.34,
      518.084,
      586.649,
      44.403,
      52.091,
      45.815,
      41.735,
      40.951,
      40.951,
      34.832,
      42.52,
      53.974,
      55.072,
      41.578,
      39.225,
      39.225,
      553.857,
      33.263,
      66.682,
      63.701,
      47.698,
      55.543,
      38.754,
      45.972,
      40.794,
      44.56,
      32.792,
      25.575,
      23.692,
      48.796,
      58.21,
      54.287,
      56.17,
      43.932,
      31.694,
      34.361,
      60.093,
      62.76,
      64.486,
      90.374,
      87.55,
      73.429,
      63.231,
      72.488,
      64.015,
      79.078,
      65.427,
      57.582,
      47.07,
      47.541,
      45.344,
      40.323,
      48.011,
      50.522,
      43.932,
      54.444,
      71.076,
      53.817,
      61.975,
      44.089,
      78.293,
      62.289,
      49.267,
      72.488,
      58.367,
      64.8,
      80.49,
      77.979,
      63.701,
      57.582,
      48.325,
      46.913,
      32.008,
      23.535,
      21.652,
      27.771,
      22.907,
      24.79,
      55.699,
      76.567,
      59.308,
      50.365,
      48.796,
      43.304,
      51.62,
      58.524,
      63.858,
      59.622,
      59.622,
      83.314,
      78.764,
      76.724,
      53.189,
      55.699,
      73.743,
      75.469,
      96.493,
      93.669,
      91.63,
      76.724,
      68.408,
      55.229,
      47.541,
      39.068,
      44.246,
      49.894,
      39.068,
      40.794,
      38.911
    ],
    "radio_duty_cycle": 0.317,
    "radio_duty_cycle_joined": 0.317,
    "charge_uc": 69071.908,
    "charge_joined_uc": 69071.908,
    "avg_current_uA": 9.593,
    "avg_current_joined_uA": 9.593,
    "routing_tx": 633,
    "routing_rx": 449,
    "routing_join_time_sec": 87.55,
    "routing_num_parent_changes": 77
  },
  "7": {
    "app_num_tx": 50,
    "app_num_endpoint_rx": 10,
    "app_num_lost": 23,
    "app_reliability": 30.303030303030297,
    "app_num_queue_drops": 11,
    "app_num_tx_limit_drops": 0,
    "app_num_routing_drops": 12,
    "app_num_scheduling_drops": 0,
    "app_num_other_drops": 0,
    "tsch_eb_tx": 30,
    "tsch_eb_rx": 16,
    "tsch_keepalive_tx": 0,
    "tsch_keepalive_rx": 0,
    "mac_tx": 715,
    "mac_tx_unicast": 389,
    "mac_acked": 254,
    "mac_rx": 705,
    "mac_rx_error": 213,
    "mac_rx_collision": 1546,
    "mac_ack_error": 3,
    "mac_parent_tx_unicast": 249,
    "mac_parent_acked": 119,
    "mac_parent_rx": 121,
    "slots_rx_idle": 3058,
    "slots_rx_scanning": 0,
    "slots_rx_packet": 424,
    "slots_rx_packet_tx_ack": 265,
    "slots_tx_packet": 326,
    "slots_tx_packet_rx_ack": 389,
    "tsch_join_time_sec": 0,
    "tsch_num_parent_changes": 91,
    "app_latency_min_s": 48.011,
    "app_latency_avg_s": 323.4806,
    "app_latency_max_s": 1210.64,
    "app_latencies": [
      101.828,
      86.138,
      75.155,
      61.819,
      65.27,
      64.015,
      48.011,
      1210.64,
      532.205,
      989.725
    ],
    "radio_duty_cycle": 0.306,
    "radio_duty_cycle_joined": 0.306,
    "charge_uc": 66715.697,
    "charge_joined_uc": 66715.697,
    "avg_current_uA": 9.266,
    "avg_current_joined_uA": 9.266,
    "routing_tx": 660,
    "routing_rx": 505,
    "routing_join_time_sec": 58.367,
    "routing_num_parent_changes": 91
  },
  "8": {
    "app_num_tx": 409,
    "app_num_endpoint_rx": 374,
    "app_num_lost": 32,
    "app_reliability": 92.11822660098522,
    "app_num_queue_drops": 7,
    "app_num_tx_limit_drops": 6,
    "app_num_routing_drops": 19,
    "app_num_scheduling_drops": 0,
    "app_num_other_drops": 0,
    "tsch_eb_tx": 104,
    "tsch_eb_rx": 90,
    "tsch_keepalive_tx": 0,
    "tsch_keepalive_rx": 0,
    "mac_tx": 1900,
    "mac_tx_unicast": 1474,
    "mac_acked": 1113,
    "mac_rx": 1408,
    "mac_rx_error": 483,
    "mac_rx_collision": 1027,
    "mac_ack_error": 40,
    "mac_parent_tx_unicast": 1384,
    "mac_parent_acked": 971,
    "mac_parent_rx": 313,
    "slots_rx_idle": 2390,
    "slots_rx_scanning": 0,
    "slots_rx_packet": 482,
    "slots_rx_packet_tx_ack": 836,
    "slots_tx_packet": 426,
    "slots_tx_packet_rx_ack": 1474,
    "tsch_join_time_sec": 0,
    "tsch_num_parent_changes": 43,
    "app_latency_min_s": 0,
    "app_latency_avg_s": 24.51659625668447,
    "app_latency_max_s": 1320.784,
    "app_latencies": [
      16.004,
      15.062,
      13.493,
      17.887,
      15.533,
      2.51,
      1.412,
      3.295,
      0.157,
      1.255,
      9.571,
      13.337,
      1.883,
      0.157,
      1.255,
      7.217,
      7.531,
      0.628,
      1.098,
      0.785,
      1.726,
      10.355,
      2.04,
      9.257,
      2.04,
      0.785,
      11.297,
      1.098,
      29.497,
      10.983,
      5.648,
      1.412,
      0.471,
      0,
      1.569,
      42.049,
      29.497,
      11.924,
      5.648,
      1.098,
      50.679,
      50.365,
      32.478,
      22.28,
      12.552,
      56.013,
      44.873,
      46.129,
      33.106,
      36.087,
      15.376,
      3.922,
      2.51,
      12.081,
      0.157,
      0,
      4.864,
      0.941,
      10.983,
      9.885,
      25.104,
      24.006,
      10.669,
      42.363,
      15.847,
      5.491,
      0.157,
      9.257,
      39.696,
      34.675,
      39.225,
      49.11,
      48.168,
      66.839,
      77.038,
      71.389,
      67.624,
      58.21,
      71.546,
      60.877,
      1320.784,
      1310.586,
      1313.41,
      1306.192,
      34.675,
      18.2,
      2.981,
      3.609,
      4.864,
      4.55,
      154.546,
      50.051,
      96.18,
      79.078,
      30.595,
      4.707,
      2.51,
      2.353,
      24.319,
      20.554,
      4.707,
      2.353,
      4.55,
      3.295,
      7.06,
      8.002,
      3.766,
      2.353,
      6.433,
      4.236,
      4.236,
      5.021,
      2.667,
      3.452,
      4.079,
      4.079,
      2.51,
      2.353,
      2.824,
      2.667,
      8.159,
      16.318,
      3.766,
      3.138,
      4.864,
      3.609,
      2.51,
      6.59,
      2.981,
      4.393,
      4.864,
      8.629,
      2.51,
      8.316,
      4.236,
      3.295,
      4.55,
      3.766,
      3.452,
      4.393,
      4.393,
      3.609,
      12.081,
      5.648,
      2.51,
      2.51,
      4.55,
      5.491,
      2.824,
      5.805,
      10.826,
      8.159,
      3.452,
      3.138,
      9.414,
      5.805,
      7.845,
      3.138,
      2.824,
      8.473,
      9.571,
      2.51,
      2.824,
      9.885,
      10.983,
      4.236,
      5.178,
      10.355,
      6.276,
      5.021,
      10.826,
      9.1,
      7.531,
      10.826,
      16.631,
      14.278,
      13.336,
      7.531,
      10.355,
      12.709,
      13.65,
      4.55,
      4.864,
      11.14,
      8.002,
      7.374,
      5.962,
      4.707,
      3.922,
      3.922,
      3.452,
      4.236,
      2.824,
      4.236,
      2.824,
      2.667,
      4.864,
      4.393,
      2.51,
      2.981,
      7.06,
      4.236,
      3.138,
      2.824,
      5.648,
      2.667,
      4.393,
      7.688,
      7.374,
      3.138,
      4.707,
      3.922,
      4.079,
      2.981,
      4.864,
      4.393,
      4.079,
      2.667,
      4.864,
      4.079,
      3.922,
      4.864,
      2.824,
      4.393,
      2.824,
      4.079,
      3.138,
      9.1,
      3.295,
      3.766,
      2.667,
      4.707,
      8.943,
      7.217,
      3.452,
      3.922,
      5.962,
      4.079,
      3.295,
      3.295,
      4.079,
      6.119,
      3.922,
      4.393,
      4.55,
      4.864,
      3.452,
      4.236,
      3.766,
      11.611,
      5.805,
      3.295,
      3.452,
      10.042,
      4.079,
      6.433,
      4.55,
      10.198,
      5.335,
      7.688,
      8.316,
      5.021,
      8.629,
      2.51,
      8.002,
      3.609,
      5.962,
      9.1,
      11.14,
      3.295,
      2.981,
      9.885,
      3.452,
      12.081,
      19.299,
      15.847,
      21.966,
      10.042,
      7.374,
      5.178,
      4.236,
      10.512,
      6.747,
      6.59,
      6.747,
      7.845,
      8.002,
      7.06,
      7.531,
      7.06,
      4.393,
      7.688,
      9.414,
      6.904,
      5.335,
      5.335,
      6.276,
      8.316,
      6.276,
      5.335,
      8.159,
      11.14,
      17.102,
      10.042,
      8.786,
      11.767,
      10.042,
      8.159,
      6.904,
      6.276,
      5.648,
      4.55,
      7.845,
      10.669,
      12.081,
      12.552,
      10.198,
      12.081,
      9.885,
      4.236,
      5.021,
      2.981,
      13.023,
      12.238,
      14.592,
      18.828,
      15.69,
      2.981,
      4.236,
      3.138,
      9.257,
      9.414,
      8.159,
      9.571,
      13.65,
      4.079,
      9.1,
      8.159,
      2.981,
      6.747,
      10.669,
      21.025,
      17.259,
      13.023,
      23.692,
      15.533,
      14.905,
      23.064,
      13.023,
      7.845,
      7.845,
      7.845,
      6.119,
      2.824,
      4.55,
      2.51,
      2.353,
      4.393,
      4.079,
      3.922,
      4.236,
      4.079,
      6.276,
      6.433,
      3.452,
      3.138,
      3.922,
      4.864,
      8.159,
      2.353,
      4.55,
      2.981,
      4.393,
      3.922
    ],
    "radio_duty_cycle": 0.239,
    "radio_duty_cycle_joined": 0.239,
    "charge_uc": 52142.091,
    "charge_joined_uc": 52142.091,
    "avg_current_uA": 7.242,
    "avg_current_joined_uA": 7.242,
    "routing_tx": 680,
    "routing_rx": 641,
    "routing_join_time_sec": 111.87,
    "routing_num_parent_changes": 43
  },
  "global-stats for this duration": {
    "app-packets-sent": [
      {
        "total": 1643,
        "name": "Number of application packets sent"
      }
    ],
    "app-packets-received": [
      {
        "total": 1342,
        "name": "Number of application packets received"
      }
    ],
    "app-packets-lost": [
      {
        "total": 214,
        "name": "Number of application packets lost"
      }
    ],
    "current-consumed": [
      {
        "name": "Current consumed",
        "unit": "mA",
        "mean": 0.064
      }
    ],
    "current-consumed-when-joined": [
      {
        "name": "Current consumed",
        "unit": "mA",
        "mean": 0.064
      }
    ],
    "e2e-delivery": [
      {
        "value": 86.24678663239075,
        "name": "E2E delivery ratio",
        "unit": "%"
      },
      {
        "value": 13.753213367609249,
        "name": "E2E loss ratio",
        "unit": "%"
      }
    ],
    "e2e-latency": [
      {
        "name": "E2E latency",
        "min": 0,
        "max": 2020.401,
        "unit": "s",
        "mean": 34.847059612518635
      }
    ]
  }
}